sound_player/__init__.py
sound_player/android.py
sound_player/common.py
sound_player/player.py
sound_player/sound.py
sound_player-0.5.1.dist-info/LICENSE
sound_player-0.5.1.dist-info/METADATA
sound_player-0.5.1.dist-info/WHEEL
sound_player-0.5.1.dist-info/top_level.txt
sound_player-0.5.1.dist-info/RECORD
