Metadata-Version: 2.2
Name: sound-player
Version: 0.5.1
Summary: The aim of this project is to create multi playlist player
Home-page: https://github.com/Krozark/sound-player
Author: Maxime Barbier
Author-email: maxime.barbier1991+ava@gmail.com
License: BSD2
Keywords: sound player
Classifier: Programming Language :: Python
Classifier: Programming Language :: Python :: 3
Classifier: Operating System :: OS Independent
Requires-Python: >=3.6
License-File: LICENSE
Requires-Dist: python-vlc
Dynamic: author
Dynamic: author-email
Dynamic: classifier
Dynamic: description
Dynamic: description-content-type
Dynamic: home-page
Dynamic: keywords
Dynamic: license
Dynamic: requires-dist
Dynamic: requires-python
Dynamic: summary
